pelican/plugins/social_cards/__init__.py
pelican/plugins/social_cards/cards_generator.py
pelican/plugins/social_cards/settings.py
pelican/plugins/social_cards/social_cards.py
pelican_social_cards-0.6.4.dist-info/METADATA
pelican_social_cards-0.6.4.dist-info/WHEEL
pelican_social_cards-0.6.4.dist-info/RECORD
