Metadata-Version: 2.3
Name: pelican-social-cards
Version: 0.6.4
Summary: Plugin to generate social media cards with post title embedded
License: AGPL-3.0
Keywords: pelican,plugin
Author: Mirek Długosz
Author-email: mirek@mirekdlugosz.com
Requires-Python: >=3.9
Classifier: Development Status :: 4 - Beta
Classifier: Environment :: Console
Classifier: Framework :: Pelican
Classifier: Framework :: Pelican :: Plugins
Classifier: Intended Audience :: End Users/Desktop
Classifier: License :: OSI Approved :: GNU Affero General Public License v3
Classifier: Operating System :: OS Independent
Classifier: Programming Language :: Python :: 3.9
Classifier: Programming Language :: Python :: 3.10
Classifier: Programming Language :: Python :: 3.11
Classifier: Programming Language :: Python :: 3.12
Classifier: Programming Language :: Python :: 3.13
Classifier: Topic :: Internet :: WWW/HTTP
Classifier: Topic :: Software Development :: Libraries :: Python Modules
Provides-Extra: lint
Provides-Extra: markdown
Provides-Extra: test
Requires-Dist: invoke (>=2.2) ; extra == "lint"
Requires-Dist: markdown (>=3.4) ; extra == "markdown"
Requires-Dist: markdown (>=3.4) ; extra == "test"
Requires-Dist: pelican (>=4.5)
Requires-Dist: pillow (>=11.1,<12.0)
Requires-Dist: pytest (>=7.0) ; extra == "test"
Requires-Dist: pytest-cov (>=4.0) ; extra == "test"
Requires-Dist: pytest-sugar (>=1.0) ; extra == "test"
Requires-Dist: ruff (>=0.9.1,<1.0.0) ; extra == "lint"
Project-URL: Homepage, https://github.com/mirekdlugosz/pelican-social-cards
Project-URL: Repository, https://github.com/mirekdlugosz/pelican-social-cards
